p2j.py
p2j/__init__.py
p2j/__main__.py
p2j/p2j.py
p2j/examples/example.ipynb
p2j/examples/example.py
p2j/examples/example2.ipynb
p2j/examples/example2.py
p2j/examples/example3.ipynb
p2j/examples/example3.py
p2j/templates/cell_code.json
p2j/templates/cell_markdown.json
p2j/templates/metadata.json
p2j-1.3.2.dist-info/METADATA
p2j-1.3.2.dist-info/RECORD
p2j-1.3.2.dist-info/WHEEL
p2j-1.3.2.dist-info/entry_points.txt
p2j-1.3.2.dist-info/top_level.txt
