Metadata-Version: 2.1
Name: p2j
Version: 1.3.2
Summary: p2j: Convert Python scripts to Jupyter notebook with minimal intervention
Home-page: https://github.com/raibosome/python2jupyter
Author: Raimi bin Karim
Author-email: raimi.bkarim@gmail.com
License: MIT
Keywords: convert python jupyter notebook script
Platform: UNKNOWN
Classifier: License :: OSI Approved :: MIT License
Classifier: Programming Language :: Python
Classifier: Programming Language :: Python :: 3
Classifier: Programming Language :: Python :: 3.6
Requires-Python: >=3.6.0
